efficient_rl/__init__.py
efficient_rl/dissertation_script.py
efficient_rl/paper_script.py
efficient_rl/agents/BaseAgentClass.py
efficient_rl/agents/DOORmaxClass.py
efficient_rl/agents/FactoredRmaxClass.py
efficient_rl/agents/QLearningClass.py
efficient_rl/agents/RmaxBaseClass.py
efficient_rl/agents/RmaxClass.py
efficient_rl/agents/__init__.py
efficient_rl/agents/oo_mdp_learner/CELearnerClass.py
efficient_rl/agents/oo_mdp_learner/CRLearnerClass.py
efficient_rl/agents/oo_mdp_learner/__init__.py
efficient_rl/environment/TaxiEnvironmentClass.py
efficient_rl/environment/__init__.py
efficient_rl/environment/classical_mdp/ClassicalTaxiClass.py
efficient_rl/environment/classical_mdp/__init__.py
efficient_rl/environment/factored_mdp/FactoredTaxiClass.py
efficient_rl/environment/factored_mdp/__init__.py
efficient_rl/environment/oo_mdp/OOTaxiClass.py
efficient_rl/environment/oo_mdp/TaxiRelationClass.py
efficient_rl/environment/oo_mdp/__init__.py
efficient_rl/oo_mdp_operations/OperationsClass.py
efficient_rl/oo_mdp_operations/__init__.py
efficient_rl-1.0.dist-info/LICENSE
efficient_rl-1.0.dist-info/METADATA
efficient_rl-1.0.dist-info/WHEEL
efficient_rl-1.0.dist-info/top_level.txt
efficient_rl-1.0.dist-info/RECORD
