Metadata-Version: 2.1
Name: efficient-rl
Version: 1.0
Summary: Reimplementation of Diuks "object-oriented representation for efficient RL".
Home-page: https://github.com/borea17/efficient_rl
Author: Markus Borea
Author-email: UNKNOWN
License: MIT
Download-URL: https://github.com/borea17/efficient_rl/archive/v_1.0.tar.gz
Keywords: Reinforcement Learning,Efficient RL,OO-MDP
Platform: UNKNOWN
Classifier: Programming Language :: Python :: 3
Classifier: License :: OSI Approved :: MIT License
Classifier: Operating System :: OS Independent
Requires-Dist: numpy
Requires-Dist: pandas
Requires-Dist: networkx
Requires-Dist: gym
Requires-Dist: matplotlib
Requires-Dist: prettytable
